.editorconfig
.gitignore
LICENSE
MANIFEST.in
README.rst
setup.py
.github/ISSUE_TEMPLATE.md
docs/Makefile
docs/conf.py
docs/index.rst
docs/requirements.txt
examples/SW_of_Roesslers.py
examples/benchmark.py
examples/double_fhn_example.py
examples/double_fhn_lyapunov.py
examples/double_fhn_restricted_lyap.py
examples/double_fhn_transversal_lyap.py
examples/kuramoto_network.py
examples/lotka_volterra.py
jitcode/__init__.py
jitcode/_jitcode.py
jitcode/integrator_tools.py
jitcode/jitced_template.c
jitcode/sympy_symbols.py
jitcode/version.py
jitcode.egg-info/PKG-INFO
jitcode.egg-info/SOURCES.txt
jitcode.egg-info/dependency_links.txt
jitcode.egg-info/requires.txt
jitcode.egg-info/top_level.txt
tests/all_tests.sh
tests/scenarios.py
tests/test_generation.py
tests/test_integrator_tools.py
tests/test_jitcode.py
tests/test_order.py
tests/test_sympy_input.py
tests/test_transversal_lyap.py