Metadata-Version: 2.1
Name: jitcode
Version: 1.7.2
Summary: Just-in-Time Compilation for Ordinary Differential Equations
Home-page: http://github.com/neurophysik/jitcode
Author: Gerrit Ansmann
Author-email: gansmann@uni-bonn.de
License: UNKNOWN
Platform: UNKNOWN
Classifier: Development Status :: 4 - Beta
Classifier: License :: OSI Approved :: BSD License
Classifier: Operating System :: POSIX
Classifier: Operating System :: MacOS :: MacOS X
Classifier: Operating System :: Microsoft :: Windows
Classifier: Programming Language :: Python
Classifier: Topic :: Scientific/Engineering :: Mathematics
Requires-Python: >=3.3
License-File: LICENSE
